leo_prompt_optimizer/__init__.py
leo_prompt_optimizer/optimizer.py
leo_prompt_optimizer/optimizer_old.py
leo_prompt_optimizer-0.1.7.dist-info/METADATA
leo_prompt_optimizer-0.1.7.dist-info/WHEEL
leo_prompt_optimizer-0.1.7.dist-info/top_level.txt
leo_prompt_optimizer-0.1.7.dist-info/RECORD
