Metadata-Version: 2.4
Name: leo-prompt-optimizer
Version: 0.1.7
Summary: A Python library to optimize prompt drafts using LLMs
Author: Léonard Baesen-Wagner
Author-email: Leonard Baesen-Wagner <lr.baesen@gmail.com>
License: MIT
Requires-Python: >=3.8
Requires-Dist: groq
Requires-Dist: python-dotenv
Dynamic: author
Dynamic: requires-python
